{
  "id": "uavcan.equipment.gnss.RTCMStream",
  "description": "GNSS RTCM SC-104 protocol raw stream container.\nRTCM messages that are longer than max data size can be split over multiple consecutive messages.",
  "type": "message",
  "message": {
    "variables": [
      {
        "type": "var",
        "kind": "int",
        "unsigned": true,
        "bits": 8,
        "name": "protocolIdRtcm2",
        "description": "= 2"
      },
      {
        "type": "var",
        "kind": "int",
        "unsigned": true,
        "bits": 8,
        "name": "protocolIdRtcm3",
        "description": "= 3"
      },
      {
        "type": "var",
        "kind": "int",
        "unsigned": true,
        "bits": 8,
        "name": "protocolId",
        "description": ""
      },
      {
        "length": 128,
        "range": true,
        "type": "array",
        "kind": {
          "type": "var",
          "kind": "int",
          "unsigned": true,
          "bits": 8
        },
        "name": "data",
        "description": ""
      }
    ],
    "statics": [
      "uint8 PROTOCOL_ID_UNKNOWN = 0"
    ]
  },
  "info": {
    "dataTypeID": 1062,
    "hash": "1f56030ecb171501",
    "maxBitsLength": 1040,
    "type": "object"
  }
}